mds_mdslibvirt-0.1.1.dist-info/DESCRIPTION.rst
mds_mdslibvirt-0.1.1.dist-info/METADATA
mds_mdslibvirt-0.1.1.dist-info/RECORD
mds_mdslibvirt-0.1.1.dist-info/WHEEL
mds_mdslibvirt-0.1.1.dist-info/metadata.json
mds_mdslibvirt-0.1.1.dist-info/top_level.txt
mdslibvirt/__init__.py
mdslibvirt/libvirtlib.py
mdslibvirt/runfunc.py
